ssimulacra2/__init__.py
ssimulacra2/cli.py
ssimulacra2/ssimulacra2.py
ssimulacra2-0.3.0.dist-info/METADATA
ssimulacra2-0.3.0.dist-info/WHEEL
ssimulacra2-0.3.0.dist-info/entry_points.txt
ssimulacra2-0.3.0.dist-info/licenses/LICENSE
ssimulacra2-0.3.0.dist-info/RECORD
