Metadata-Version: 2.4
Name: ssimulacra2
Version: 0.3.0
Summary: Python implementation of SSIMULACRA2 image quality metric
Project-URL: Documentation, https://github.com/Pacidus/py-ssimulacra2#readme
Project-URL: Issues, https://github.com/Pacidus/py-ssimulacra2/issues
Project-URL: Source, https://github.com/Pacidus/py-ssimulacra2
Author-email: Pacidus <Pacidus@gmail.com>
License: BSD 3-Clause License
License-File: LICENSE
Keywords: compression,image quality,perception,ssim,ssimulacra2
Classifier: Development Status :: 4 - Beta
Classifier: License :: OSI Approved :: BSD License
Classifier: Programming Language :: Python
Classifier: Programming Language :: Python :: 3.8
Classifier: Programming Language :: Python :: 3.9
Classifier: Programming Language :: Python :: 3.10
Classifier: Programming Language :: Python :: 3.11
Classifier: Programming Language :: Python :: 3.12
Classifier: Programming Language :: Python :: 3.13
Classifier: Programming Language :: Python :: Implementation :: CPython
Classifier: Topic :: Multimedia :: Graphics
Classifier: Topic :: Scientific/Engineering :: Image Processing
Requires-Python: >=3.8
Requires-Dist: numpy>=1.19.0
Requires-Dist: pillow>=8.0.0
Requires-Dist: scipy>=1.5.0
